{
  "clauseId": "7",
  "clauseNumber": "7",
  "title": "Plant, Materials and Workmanship",
  "level": 1,
  "summary": "Clause 7                               Plant, Materials and Workmanship",
  "fullText": "Clause 7                               Plant, Materials and Workmanship\n\n         Additional Sub-Clause\n\n         If the Contract is being financed by an institution whose rules or policies require a restriction on the\n         use of its funds, a further sub-clause may be added:\n\n         EXAMPLE SUB-CLAUSE\n                                            All Goods shall have their origin in eligible source countries as defined in\n\n                                            (insert name of published guidelines for procurement).\n\n                                            Goods shall be transported by carriers from these eligible source\n                                            countries, unless exempted by the Employer in writing on the basis of\n                                            potential excessive costs or delays. Surety, insurance and banking\n                                            services shall be provided by insurers and bankers from the eligible\n                                            source countries.",
  "obligations": [
    {
      "party": "Employer",
      "action": "shall",
      "description": "Goods shall be transported by carriers from these eligible source\n                                            countries, unless exempted by the Employer in writing on the basis of\n                    "
    }
  ],
  "relatedClauses": [
    "7"
  ],
  "keywords": [
    "all goods",
    "clause",
    "clause\n\n         if",
    "contract",
    "employer",
    "goods",
    "materials",
    "plant",
    "surety",
    "workmanship",
    "workmanship\n\n         additional sub"
  ],
  "parties": [
    "Employer"
  ],
  "metadata": {
    "section": "General Conditions",
    "importance": "low",
    "category": "technical",
    "hasSubClauses": false,
    "references": {
      "crossReferences": [
        "7"
      ],
      "externalDocs": [
        "Contract"
      ]
    }
  },
  "subClauses": []
}