{
  "clauseId": "17",
  "clauseNumber": "17",
  "title": "Risk and Responsibility",
  "level": 1,
  "summary": "Clause 17                              Risk and Responsibility\n        Sub-Clause 17.6                     Limitation of Liability",
  "fullText": "Clause 17                              Risk and Responsibility\n        Sub-Clause 17.6                     Limitation of Liability\n\n        EXAMPLE\n                                            In Sub-Clause 17.6, the sum referred to in the penultimate sentence\n                                            shall be\n\n        Additional Sub-Clause Use of Employer's Accommodation/Facilities\n\n        If the Contractor is to occupy the Employer's facilities temporarily, an additional sub-clause may be\n        added:\n\n        EXAMPLE SUB-CLAUSE\n                                            The Contractor shall take full responsibility for the care of the items\n                                            detailed below, from the respective dates of use or occupation by the\n                                            Contractor, up to the respective dates of hand-over or cessation of\n                                            occupation (where hand-over or cessation of occupation may take\n                                            place after the date stated in the Taking-Over Certificate for the\n                                            Works):\n\n                                            (insert details)\n\n                                            If any loss or damage happens to any of the above items while the\n                                            Contractor is responsible for their care, arising from any cause\n                                            whatsoever other than those for which the Employer is liable, the\n                                            Contractor shall, at his own cost, rectify the loss or damage to the\n18       except: example text between lines may be copied\n\f                                      satisfaction of the Engineer.",
  "obligations": [
    {
      "party": "Contractor",
      "action": "shall",
      "description": "Clause 17                              Risk and Responsibility\n        Sub-Clause 17.6                     Limitation of Liability\n\n        EXAMPLE\n                                            In Sub-C"
    },
    {
      "party": "Employer",
      "action": "shall",
      "description": "Clause 17                              Risk and Responsibility\n        Sub-Clause 17.6                     Limitation of Liability\n\n        EXAMPLE\n                                            In Sub-C"
    },
    {
      "party": "Engineer",
      "action": "shall",
      "description": "Clause 17                              Risk and Responsibility\n        Sub-Clause 17.6                     Limitation of Liability\n\n        EXAMPLE\n                                            In Sub-C"
    }
  ],
  "relatedClauses": [
    "17",
    "17.6"
  ],
  "keywords": [
    "accommodation",
    "additional sub",
    "clause",
    "clause use",
    "contractor",
    "employer",
    "engineer",
    "facilities\n\n        if",
    "in sub",
    "liability",
    "limitation",
    "over certificate",
    "responsibility",
    "responsibility\n        sub",
    "risk"
  ],
  "parties": [
    "Contractor",
    "Employer",
    "Engineer"
  ],
  "metadata": {
    "section": "General Conditions",
    "importance": "medium",
    "category": "legal",
    "hasSubClauses": false,
    "references": {
      "crossReferences": [
        "17",
        "17.6"
      ],
      "externalDocs": [
        "Contract"
      ]
    }
  },
  "subClauses": []
}